pydantic_devtools-0.3.0.dist-info/METADATA
pydantic_devtools-0.3.0.dist-info/WHEEL
pydantic_devtools-0.3.0.dist-info/entry_points.txt
pydantic_devtools-0.3.0.dist-info/licenses/LICENSE
pydantic_devtools/__init__.py
pydantic_devtools/_utils.py
pydantic_devtools/pretty_print.py
pydantic_devtools/pydantic_pdb.py
pydantic_devtools-0.3.0.dist-info/RECORD
